MANIFEST.in
README
distribute_setup.py
setup.py
postmark/__init__.py
postmark/core.py
postmark/django_backend.py
python_postmark.egg-info/PKG-INFO
python_postmark.egg-info/SOURCES.txt
python_postmark.egg-info/dependency_links.txt
python_postmark.egg-info/top_level.txt