Metadata-Version: 1.1
Name: python-postmark
Version: 0.3.2
Summary: Postmark library for Python 2.4 and greater.
Home-page: http://github.com/themartorana/python-postmark
Author: Dave Martorana (http://davemartorana.com), Richard Cooper (http://frozenskys.com), Bill Jones (oraclebill), Dmitry Golomidov (deeGraYve)
Author-email: UNKNOWN
License: BSD
Platform: UNKNOWN
Classifier: Development Status :: 4 - Beta
Classifier: Environment :: Web Environment
Classifier: Intended Audience :: Developers
Classifier: Operating System :: OS Independent
Classifier: Programming Language :: Python
